climate_learn/__init__.py
climate_learn/data/__init__.py
climate_learn/data/climatebench_dataset.py
climate_learn/data/climatebench_module.py
climate_learn/data/download.py
climate_learn/data/iterdataset.py
climate_learn/data/itermodule.py
climate_learn/data/mapmodule.py
climate_learn/data/module.py
climate_learn/data/npzdataset.py
climate_learn/data/climate_dataset/__init__.py
climate_learn/data/climate_dataset/climate_dataset.py
climate_learn/data/climate_dataset/cmip6_iterdataset.py
climate_learn/data/climate_dataset/era5_continuous_iterdataset.py
climate_learn/data/climate_dataset/era5_iterdataset.py
climate_learn/data/climate_dataset/stacked_climate_dataset.py
climate_learn/data/climate_dataset/args/__init__.py
climate_learn/data/climate_dataset/args/climate_dataset_args.py
climate_learn/data/climate_dataset/args/era5_args.py
climate_learn/data/climate_dataset/args/stacked_climate_dataset_args.py
climate_learn/data/climate_dataset/cmip6/constants.py
climate_learn/data/climate_dataset/era5/__init__.py
climate_learn/data/climate_dataset/era5/constants.py
climate_learn/data/climate_dataset/era5/era5.py
climate_learn/data/dataset/__init__.py
climate_learn/data/dataset/map_dataset.py
climate_learn/data/dataset/shard_dataset.py
climate_learn/data/dataset/args/__init__.py
climate_learn/data/dataset/args/map_dataset_args.py
climate_learn/data/dataset/args/shard_dataset_args.py
climate_learn/data/processing/climatebench.py
climate_learn/data/processing/cmip6_constants.py
climate_learn/data/processing/era5_constants.py
climate_learn/data/processing/era5_cropped.py
climate_learn/data/processing/era5_extreme.py
climate_learn/data/processing/nc2npz.py
climate_learn/data/processing/prism.py
climate_learn/data/task/__init__.py
climate_learn/data/task/downscaling.py
climate_learn/data/task/forecasting.py
climate_learn/data/task/task.py
climate_learn/data/task/args/__init__.py
climate_learn/data/task/args/downscaling_args.py
climate_learn/data/task/args/forecasting_args.py
climate_learn-1.0.0.dist-info/LICENSE
climate_learn-1.0.0.dist-info/METADATA
climate_learn-1.0.0.dist-info/WHEEL
climate_learn-1.0.0.dist-info/top_level.txt
climate_learn-1.0.0.dist-info/RECORD
