Metadata-Version: 2.1
Name: climate-learn
Version: 1.0.0
Summary: ClimateLearn: Benchmarking Machine Learning for Weather and Climate Modeling
Author-email: MINT at UCLA <jason.jewik@ucla.edu>, Tung Nguyen <tungnd@cs.ucla.edu>, Jason Jewik <jason.jewik@ucla.edu>, Hritik Bansal <hbansal@ucla.edu>, Prakhar Sharma <prakhar6sharma@gmail.com>, Aditya Grover <adityag@cs.ucla.edu>
Project-URL: Source, https://github.com/aditya-grover/climate-learn
Project-URL: Issue Tracker, https://github.com/aditya-grover/climate-learn/issues
Project-URL: Documentation, https://climatelearn.readthedocs.io/en/latest/
Classifier: Development Status :: 2 - Pre-Alpha
Classifier: Programming Language :: Python :: 3
Classifier: Programming Language :: Python :: 3.8
Classifier: Programming Language :: Python :: 3.9
Classifier: Programming Language :: Python :: 3.10
Classifier: Topic :: Scientific/Engineering
Classifier: Topic :: Scientific/Engineering :: Artificial Intelligence
Classifier: Topic :: Scientific/Engineering :: Atmospheric Science
Classifier: Topic :: Software Development
Classifier: Topic :: Software Development :: Libraries
Classifier: Topic :: Software Development :: Libraries :: Python Modules
Classifier: Intended Audience :: Developers
Classifier: Intended Audience :: Education
Classifier: Intended Audience :: Science/Research
Classifier: License :: OSI Approved :: MIT License
Classifier: Operating System :: OS Independent
Requires-Python: >=3.8
License-File: LICENSE
Requires-Dist: cdsapi (>=0.5.1)
Requires-Dist: dask (>=2022.2.0)
Requires-Dist: importlib-metadata (==4.13.0)
Requires-Dist: matplotlib (>=3.5.3)
Requires-Dist: netcdf4 (>=1.6.2)
Requires-Dist: pytorch-lightning (>=1.9.0)
Requires-Dist: scikit-learn (>=1.0.2)
Requires-Dist: timm (==0.9.2)
Requires-Dist: tensorboard (==2.11.2)
Requires-Dist: wandb (>=0.13.9)
Requires-Dist: xarray (>=0.20.2)
Requires-Dist: rasterio (>=1.3.7)
Provides-Extra: dev
Requires-Dist: black (>=23.1.0) ; extra == 'dev'
Requires-Dist: flake8 (>=3.9.2) ; extra == 'dev'
Requires-Dist: pytest (>=7.2.1) ; extra == 'dev'
Requires-Dist: properscoring ; extra == 'dev'
Requires-Dist: build ; extra == 'dev'
Requires-Dist: twine ; extra == 'dev'
Provides-Extra: docs
Requires-Dist: ipython (>=7.34.0) ; extra == 'docs'
Requires-Dist: nbsphinx (>=0.8.12) ; extra == 'docs'
Requires-Dist: sphinx (>=5.3.0) ; extra == 'docs'
Requires-Dist: sphinx-rtd-theme (>=1.1.1) ; extra == 'docs'
